cclib/__init__.py
cclib/bridge/__init__.py
cclib/bridge/cclib2ase.py
cclib/bridge/cclib2biopython.py
cclib/bridge/cclib2horton.py
cclib/bridge/cclib2openbabel.py
cclib/bridge/cclib2psi4.py
cclib/bridge/cclib2pyquante.py
cclib/bridge/cclib2pyscf.py
cclib/io/__init__.py
cclib/io/ccio.py
cclib/io/cjsonreader.py
cclib/io/cjsonwriter.py
cclib/io/cmlwriter.py
cclib/io/filereader.py
cclib/io/filewriter.py
cclib/io/moldenwriter.py
cclib/io/wfxwriter.py
cclib/io/xyzreader.py
cclib/io/xyzwriter.py
cclib/method/__init__.py
cclib/method/bader.py
cclib/method/bickelhaupt.py
cclib/method/calculationmethod.py
cclib/method/cda.py
cclib/method/cspa.py
cclib/method/ddec.py
cclib/method/density.py
cclib/method/electrons.py
cclib/method/fragments.py
cclib/method/hirshfeld.py
cclib/method/lpa.py
cclib/method/mbo.py
cclib/method/moments.py
cclib/method/mpa.py
cclib/method/nuclear.py
cclib/method/opa.py
cclib/method/orbitals.py
cclib/method/population.py
cclib/method/stockholder.py
cclib/method/volume.py
cclib/parser/__init__.py
cclib/parser/adfparser.py
cclib/parser/daltonparser.py
cclib/parser/data.py
cclib/parser/fchkparser.py
cclib/parser/gamessparser.py
cclib/parser/gamessukparser.py
cclib/parser/gaussianparser.py
cclib/parser/jaguarparser.py
cclib/parser/logfileparser.py
cclib/parser/molcasparser.py
cclib/parser/molproparser.py
cclib/parser/mopacparser.py
cclib/parser/nwchemparser.py
cclib/parser/orcaparser.py
cclib/parser/psi3parser.py
cclib/parser/psi4parser.py
cclib/parser/qchemparser.py
cclib/parser/turbomoleparser.py
cclib/parser/utils.py
cclib/progress/__init__.py
cclib/progress/qt4progress.py
cclib/progress/textprogress.py
cclib/scripts/__init__.py
cclib/scripts/ccframe.py
cclib/scripts/ccget.py
cclib/scripts/ccwrite.py
cclib/scripts/cda.py
qc2champ/__init__.py
qc2champ/io/__init__.py
qc2champ/io/qcio.py
qc2champ/parser/__init__.py
qc2champ/parser/logfileparser.py
qc2champ/parser/molcas84parser.py
qc2champ-1.0.0.dist-info/LICENSE
qc2champ-1.0.0.dist-info/METADATA
qc2champ-1.0.0.dist-info/WHEEL
qc2champ-1.0.0.dist-info/entry_points.txt
qc2champ-1.0.0.dist-info/top_level.txt
qc2champ-1.0.0.dist-info/RECORD
